<?xml version='1.0' encoding='utf-8'?><m:layout id='b4ddcaff-eb63-4f43-8fae-44f763bb210d' xmlns='http://www.w3.org/1999/xhtml' xmlns:m='http://schemas.mendix.com/forms/1.0'><m:arguments><m:argument><div data-mendix-id='13.Atlas_Core.Phone_BottomBar.scrollContainer1' data-mendix-type='mxui.widget.VerticalScrollContainer' data-mendix-props='"fixed":true,"config":[{"position":"middle"},{"position":"bottom"}]' class='mx-scrollcontainer mx-scrollcontainer-vertical mx-scrollcontainer-fixed'><div class='mx-scrollcontainer-middle region-content'><div class='mx-scrollcontainer-wrapper'><div data-mx-placeholder='2baec7b7-b3ce-42ac-8deb-638a205a37ed' class='mx-placeholder'></div></div></div><div class='mx-scrollcontainer-bottom region-bottombar'><div class='mx-scrollcontainer-wrapper'><div data-mendix-id='13.Atlas_Core.Phone_BottomBar.simpleMenuBar1' data-mendix-type='mxui.widget.MenuBar' data-mendix-props='"menu":[{"id":"3d6aeca9-1f93-40dc-bfd2-80502eebb09d-0","caption":"Home","iconClass":"glyphicon-home","action":{"type":"doNothing","argMap":{},"config":{},"disabledDuringExecution":false}},{"id":"3d6aeca9-1f93-40dc-bfd2-80502eebb09d-1","caption":"Layouts","iconClass":"glyphicon-book","action":{"type":"doNothing","argMap":{},"config":{},"disabledDuringExecution":false}},{"id":"3d6aeca9-1f93-40dc-bfd2-80502eebb09d-2","caption":"Templates","iconClass":"glyphicon-file","action":{"type":"doNothing","argMap":{},"config":{},"disabledDuringExecution":false}},{"id":"3d6aeca9-1f93-40dc-bfd2-80502eebb09d-3","caption":"Widgets","iconClass":"glyphicon-cog","action":{"type":"doNothing","argMap":{},"config":{},"disabledDuringExecution":false}}],"orientation":"horizontal"' class='mx-name-simpleMenuBar1 bottom-nav-text-icons'></div></div></div></div></m:argument></m:arguments></m:layout>